{"name": "purei-play", "desktopName": "Play!", "version": "0.70", "aliases": ["purei-play"], "artifacts": {"apps": [{"source": "Play.app"}], "binaries": [], "manPages": [], "files": [], "shellCompletionsBash": [], "shellCompletionsFish": [], "shellCompletionsZsh": []}, "files": {"aarch64-darwin": {"url": "https://purei.org/downloads/play/stable/0.70/Play.dmg", "version": "0.70", "hash": "sha256-zZtk6xSc6n4GQKpESYzlc04nOsL0OIQ1rDNimw/g2Kc="}, "x86_64-darwin": {"url": "https://purei.org/downloads/play/stable/0.70/Play.dmg", "version": "0.70", "hash": "sha256-zZtk6xSc6n4GQKpESYzlc04nOsL0OIQ1rDNimw/g2Kc="}}, "meta": {"description": "PlayStation 2 emulator", "homepage": "https://purei.org/"}, "passthru": {}}