{"name": "vrew", "desktopName": "Vrew", "version": "3.2.0", "aliases": ["vrew"], "artifacts": {"apps": [{"source": "Vrew.app"}], "binaries": [], "manPages": [], "files": [], "shellCompletionsBash": [], "shellCompletionsFish": [], "shellCompletionsZsh": []}, "files": {"aarch64-darwin": {"url": "https://vrew-files.voyagerx.com/Vrew-3.2.0.dmg", "version": "3.2.0", "hash": "sha256-gZgUgukU7e4o6vh2bI9Ia6R33X9yzuS3LT5/Kt37ri8="}, "x86_64-darwin": {"url": "https://vrew-files.voyagerx.com/Vrew-3.2.0.dmg", "version": "3.2.0", "hash": "sha256-gZgUgukU7e4o6vh2bI9Ia6R33X9yzuS3LT5/Kt37ri8="}}, "meta": {"description": "Video editor", "homepage": "https://vrew.voyagerx.com/", "platforms": ["aarch64-darwin", "x86_64-darwin"]}, "passthru": {}}