{"name": "id3-editor", "desktopName": "ID3 Editor", "version": "1.29.51", "aliases": ["id3-editor"], "artifacts": {"apps": [{"source": "ID3 Editor.app"}], "binaries": [], "manPages": [], "files": [], "shellCompletionsBash": [], "shellCompletionsFish": [], "shellCompletionsZsh": []}, "files": {"aarch64-darwin": {"url": "http://www.pa-software.com/release/ID3Editor.arm.1.29.51.dmg", "version": "1.29.51", "hash": "sha256-iki1kt3fXD4OkGhZXts+OGJySW1MgeK5S7y7dGK9gHQ="}, "x86_64-darwin": {"url": "http://www.pa-software.com/release/ID3Editor.arm.1.29.51.dmg", "version": "1.29.51", "hash": "sha256-iki1kt3fXD4OkGhZXts+OGJySW1MgeK5S7y7dGK9gHQ="}}, "meta": {"description": "MP3 and AIFF ID3 tag editor", "homepage": "http://www.pa-software.com/id3editor/"}, "passthru": {}}