{"name": "waltr", "desktopName": "WALTR", "version": "2.6.27", "aliases": ["waltr"], "artifacts": {"apps": [{"source": "Waltr 2.app"}], "binaries": [], "manPages": [], "files": [], "shellCompletionsBash": [], "shellCompletionsFish": [], "shellCompletionsZsh": []}, "files": {"aarch64-darwin": {"url": "https://shining.softorino.com/shine_uploads/waltr2mac_2.6.27.dmg", "version": "2.6.27", "hash": "sha256-WxyiMkTQYMbKlB+WynjpH7/1zeNM312YeUaP7m4pKfM="}, "x86_64-darwin": {"url": "https://shining.softorino.com/shine_uploads/waltr2mac_2.6.27.dmg", "version": "2.6.27", "hash": "sha256-WxyiMkTQYMbKlB+WynjpH7/1zeNM312YeUaP7m4pKfM="}}, "meta": {"description": "Media direct transfer tool for Apple devices", "homepage": "https://softorino.com/legacy/waltr"}, "passthru": {}}