{"name": "telegram-desktop", "desktopName": "Telegram Desktop", "version": "6.0.2", "aliases": ["telegram-desktop"], "artifacts": {"apps": [{"source": "Telegram.app", "target": "Telegram Desktop.app"}], "binaries": [], "manPages": [], "files": [], "shellCompletionsBash": [], "shellCompletionsFish": [], "shellCompletionsZsh": []}, "files": {"aarch64-darwin": {"url": "https://updates.tdesktop.com/tmac/tsetup.6.0.2.dmg", "version": "6.0.2", "hash": "sha256-d+hGRKJcOW0phSRvn8sNPbOUatSqg2UCx3Kltf9SHhQ="}, "x86_64-darwin": {"url": "https://updates.tdesktop.com/tmac/tsetup.6.0.2.dmg", "version": "6.0.2", "hash": "sha256-d+hGRKJcOW0phSRvn8sNPbOUatSqg2UCx3Kltf9SHhQ="}}, "meta": {"description": "Desktop client for Telegram messenger", "homepage": "https://desktop.telegram.org/", "platforms": ["aarch64-darwin", "x86_64-darwin"], "broken": false}, "passthru": {}}