{"name": "teleport-suite", "desktopName": "Teleport", "version": "18.1.5", "aliases": ["teleport", "teleport-suite"], "artifacts": {"apps": [], "binaries": [], "manPages": [], "files": [], "shellCompletionsBash": [], "shellCompletionsFish": [], "shellCompletionsZsh": []}, "files": {"aarch64-darwin": {"url": "https://cdn.teleport.dev/teleport-18.1.5.pkg", "version": "18.1.5", "hash": "sha256-QlxRWGlMHlic6CIwmIraQZz/sCQ761QRf445Q6nd8nM="}, "x86_64-darwin": {"url": "https://cdn.teleport.dev/teleport-18.1.5.pkg", "version": "18.1.5", "hash": "sha256-QlxRWGlMHlic6CIwmIraQZz/sCQ761QRf445Q6nd8nM="}}, "meta": {"description": "Modern SSH server for teams managing distributed infrastructure", "homepage": "https://goteleport.com/"}, "passthru": {}}