{"name": "rivet", "desktopName": "Rivet", "version": "1.11.3", "aliases": ["rivet"], "artifacts": {"apps": [{"source": "Rivet.app"}], "binaries": [], "manPages": [], "files": [], "shellCompletionsBash": [], "shellCompletionsFish": [], "shellCompletionsZsh": []}, "files": {"aarch64-darwin": {"url": "https://github.com/Ironclad/rivet/releases/download/app-v1.11.3/Rivet.dmg", "version": "1.11.3", "hash": "sha256-G84xhvc7v30ZcBMhJZ5CWolweqLYLywcjCGLk6wS66A="}, "x86_64-darwin": {"url": "https://github.com/Ironclad/rivet/releases/download/app-v1.11.3/Rivet.dmg", "version": "1.11.3", "hash": "sha256-G84xhvc7v30ZcBMhJZ5CWolweqLYLywcjCGLk6wS66A="}}, "meta": {"description": "Open-source visual AI programming environment", "homepage": "https://rivet.ironcladapp.com/", "platforms": ["aarch64-darwin", "x86_64-darwin"], "broken": false}, "passthru": {}}