{"name": "cinch", "desktopName": "Cinch", "version": "1.2.4", "aliases": ["cinch"], "artifacts": {"apps": [{"source": "Cinch.app"}], "binaries": [], "manPages": [], "files": [], "shellCompletionsBash": [], "shellCompletionsFish": [], "shellCompletionsZsh": []}, "files": {"aarch64-darwin": {"url": "https://www.irradiatedsoftware.com/downloads/Cinch_1.2.4.zip", "version": "1.2.4", "hash": "sha256-aK//Gar/SIXoA3M990z8h/5lKexXEH0hvdywDWHdFKA="}, "x86_64-darwin": {"url": "https://www.irradiatedsoftware.com/downloads/Cinch_1.2.4.zip", "version": "1.2.4", "hash": "sha256-aK//Gar/SIXoA3M990z8h/5lKexXEH0hvdywDWHdFKA="}}, "meta": {"description": "Window management tool", "homepage": "https://www.irradiatedsoftware.com/cinch/", "platforms": ["aarch64-darwin", "x86_64-darwin"]}, "passthru": {}}