{"name": "font-libre-barcode-39", "desktopName": "Libre Barcode 39", "version": "latest", "aliases": ["font-libre-barcode-39"], "artifacts": {"apps": [], "binaries": [], "manPages": [], "files": [], "shellCompletionsBash": [], "shellCompletionsFish": [], "shellCompletionsZsh": []}, "files": {"aarch64-darwin": null, "x86_64-darwin": null}, "meta": {"description": null, "homepage": "https://fonts.google.com/specimen/Libre+Barcode+39", "platforms": ["aarch64-darwin", "x86_64-darwin"]}, "passthru": {}}