{"name": "font-im-fell-double-pica", "desktopName": "IM Fell Double Pica", "version": "latest", "aliases": ["font-im-fell-double-pica"], "artifacts": {"apps": [], "binaries": [], "manPages": [], "files": [], "shellCompletionsBash": [], "shellCompletionsFish": [], "shellCompletionsZsh": []}, "files": {"aarch64-darwin": null, "x86_64-darwin": null}, "meta": {"description": null, "homepage": "https://fonts.google.com/specimen/IM+Fell+Double+Pica", "platforms": ["aarch64-darwin", "x86_64-darwin"]}, "passthru": {}}