{"name": "font-ubuntu-sans-nerd-font", "desktopName": "UbuntuSans Nerd Font families (Ubuntu Sans)", "version": "3.4.0", "aliases": ["font-ubuntu-sans-nerd-font"], "artifacts": {"apps": [], "binaries": [], "manPages": [], "files": [], "shellCompletionsBash": [], "shellCompletionsFish": [], "shellCompletionsZsh": []}, "files": {"aarch64-darwin": {"url": "https://github.com/ryanoasis/nerd-fonts/releases/download/v3.4.0/UbuntuSans.zip", "version": "3.4.0", "hash": "sha256-EWbiZm2j7k8ETjLdHfwI2n+d2qaYn8Gwy8GKeEeUNNc="}, "x86_64-darwin": {"url": "https://github.com/ryanoasis/nerd-fonts/releases/download/v3.4.0/UbuntuSans.zip", "version": "3.4.0", "hash": "sha256-EWbiZm2j7k8ETjLdHfwI2n+d2qaYn8Gwy8GKeEeUNNc="}}, "meta": {"description": null, "homepage": "https://github.com/ryanoasis/nerd-fonts", "platforms": ["aarch64-darwin", "x86_64-darwin"]}, "passthru": {}}