{"name": "font-iosevka-ss11", "desktopName": "Iosevka SS11", "version": "33.2.8", "aliases": ["font-iosevka-ss11"], "artifacts": {"apps": [], "binaries": [], "manPages": [], "files": [], "shellCompletionsBash": [], "shellCompletionsFish": [], "shellCompletionsZsh": []}, "files": {"aarch64-darwin": {"url": "https://github.com/be5invis/Iosevka/releases/download/v33.2.8/SuperTTC-IosevkaSS11-33.2.8.zip", "version": "33.2.8", "hash": "sha256-Izo6nIt9TP5RVUMilyoRJ7qUgTzgnhqRVk86c/HN//Y="}, "x86_64-darwin": {"url": "https://github.com/be5invis/Iosevka/releases/download/v33.2.8/SuperTTC-IosevkaSS11-33.2.8.zip", "version": "33.2.8", "hash": "sha256-Izo6nIt9TP5RVUMilyoRJ7qUgTzgnhqRVk86c/HN//Y="}}, "meta": {"description": null, "homepage": "https://github.com/be5invis/Iosevka/", "platforms": ["aarch64-darwin", "x86_64-darwin"]}, "passthru": {}}