{"name": "font-tt2020", "desktopName": "TT2020", "version": "0.2.1", "aliases": ["font-tt2020"], "artifacts": {"apps": [], "binaries": [], "manPages": [], "files": [], "shellCompletionsBash": [], "shellCompletionsFish": [], "shellCompletionsZsh": []}, "files": {"aarch64-darwin": {"url": "https://github.com/ctrlcctrlv/TT2020/archive/refs/tags/v0.2.1.tar.gz", "version": "0.2.1", "hash": "sha256-psNKf/zm4vh8ElZnJAKb3lKDZM5lOAWsPSijSEXYFec="}, "x86_64-darwin": {"url": "https://github.com/ctrlcctrlv/TT2020/archive/refs/tags/v0.2.1.tar.gz", "version": "0.2.1", "hash": "sha256-psNKf/zm4vh8ElZnJAKb3lKDZM5lOAWsPSijSEXYFec="}}, "meta": {"description": null, "homepage": "https://github.com/ctrlcctrlv/TT2020"}, "passthru": {}}