{"name": "font-playpen-sans-deva", "desktopName": "Playpen Sans Deva", "version": "latest", "aliases": ["font-playpen-sans-deva"], "artifacts": {"apps": [], "binaries": [], "manPages": [], "files": [], "shellCompletionsBash": [], "shellCompletionsFish": [], "shellCompletionsZsh": []}, "files": {"aarch64-darwin": null, "x86_64-darwin": null}, "meta": {"description": null, "homepage": "https://fonts.google.com/specimen/Playpen+Sans+Deva", "platforms": ["aarch64-darwin", "x86_64-darwin"]}, "passthru": {}}