{"name": "font-kolker-brush", "desktopName": "Kolker Brush", "version": "latest", "aliases": ["font-kolker-brush"], "artifacts": {"apps": [], "binaries": [], "manPages": [], "files": [], "shellCompletionsBash": [], "shellCompletionsFish": [], "shellCompletionsZsh": []}, "files": {"aarch64-darwin": null, "x86_64-darwin": null}, "meta": {"description": null, "homepage": "https://fonts.google.com/specimen/Kolker+Brush", "platforms": ["aarch64-darwin", "x86_64-darwin"], "broken": true}, "passthru": {}}