{"name": "font-glow-sans-sc-compressed", "desktopName": "Glow Sans SC Compressed", "version": "0.93", "aliases": ["font-glow-sans-sc-compressed"], "artifacts": {"apps": [], "binaries": [], "manPages": [], "files": [], "shellCompletionsBash": [], "shellCompletionsFish": [], "shellCompletionsZsh": []}, "files": {"aarch64-darwin": {"url": "https://github.com/welai/glow-sans/releases/download/v0.93/GlowSansSC-Compressed-v0.93.zip", "version": "0.93", "hash": "sha256-/g+jgsj1vowWMsvFg399o3MLGLTboS01GBLQfW1rtW8="}, "x86_64-darwin": {"url": "https://github.com/welai/glow-sans/releases/download/v0.93/GlowSansSC-Compressed-v0.93.zip", "version": "0.93", "hash": "sha256-/g+jgsj1vowWMsvFg399o3MLGLTboS01GBLQfW1rtW8="}}, "meta": {"description": null, "homepage": "https://github.com/welai/glow-sans"}, "passthru": {}}