{"name": "font-bitcount-single-ink", "desktopName": "Bitcount Single Ink", "version": "latest", "aliases": ["font-bitcount-single-ink"], "artifacts": {"apps": [], "binaries": [], "manPages": [], "files": [], "shellCompletionsBash": [], "shellCompletionsFish": [], "shellCompletionsZsh": []}, "files": {"aarch64-darwin": null, "x86_64-darwin": null}, "meta": {"description": null, "homepage": "https://github.com/petrvanblokland/TYPETR-Bitcount", "platforms": ["aarch64-darwin", "x86_64-darwin"], "broken": true}, "passthru": {}}