{"name": "bilimini", "desktopName": "bilimini", "version": "1.5.7", "aliases": ["bilimini"], "artifacts": {"apps": [{"source": "bilimini.app"}], "binaries": [], "manPages": [], "files": [], "shellCompletionsBash": [], "shellCompletionsFish": [], "shellCompletionsZsh": []}, "files": {"aarch64-darwin": {"url": "https://github.com/chitosai/bilimini/releases/download/v1.5.7/bilimini-1.5.7-mac.zip", "version": "1.5.7", "hash": "sha256-1skjYiU8DUHKvTRAsucuJbsNoVfSv4fH75ieT/KKFWM="}, "x86_64-darwin": {"url": "https://github.com/chitosai/bilimini/releases/download/v1.5.7/bilimini-1.5.7-mac.zip", "version": "1.5.7", "hash": "sha256-1skjYiU8DUHKvTRAsucuJbsNoVfSv4fH75ieT/KKFWM="}}, "meta": {"description": "Small window bilibili client", "homepage": "https://github.com/chitosai/bilimini"}, "passthru": {}}