{"name": "parallels@18", "desktopName": "Parallels Desktop", "version": "18.3.3-53627", "aliases": ["parallels@18"], "artifacts": {"apps": [{"source": "Parallels Desktop.app"}], "binaries": [], "manPages": [], "files": [], "shellCompletionsBash": [], "shellCompletionsFish": [], "shellCompletionsZsh": []}, "files": {"aarch64-darwin": {"url": "https://download.parallels.com/desktop/v18/18.3.3-53627/ParallelsDesktop-18.3.3-53627.dmg", "version": "18.3.3-53627", "hash": "sha256-O0UbrLSqEhUTTQYfKsJtLJt3ysgZkSmwisJol1J3qi8="}, "x86_64-darwin": {"url": "https://download.parallels.com/desktop/v18/18.3.3-53627/ParallelsDesktop-18.3.3-53627.dmg", "version": "18.3.3-53627", "hash": "sha256-O0UbrLSqEhUTTQYfKsJtLJt3ysgZkSmwisJol1J3qi8="}}, "meta": {"description": "Desktop virtualization software", "homepage": "https://www.parallels.com/products/desktop/"}, "passthru": {}}