{"name": "macdropany", "desktopName": "MacDropAny", "version": "3.0.2", "aliases": ["macdropany"], "artifacts": {"apps": [{"source": "MacDropAny.app"}], "binaries": [], "manPages": [], "files": [], "shellCompletionsBash": [], "shellCompletionsFish": [], "shellCompletionsZsh": []}, "files": {"aarch64-darwin": {"url": "https://github.com/sebthedev/MacDropAny/releases/download/v3.0.2/MacDropAny.3.0.2.zip", "version": "3.0.2", "hash": "sha256-R8hCwdUly+ASr5TDv4LQO3Si4fZV8qIiaWiXxWIo6XQ="}, "x86_64-darwin": {"url": "https://github.com/sebthedev/MacDropAny/releases/download/v3.0.2/MacDropAny.3.0.2.zip", "version": "3.0.2", "hash": "sha256-R8hCwdUly+ASr5TDv4LQO3Si4fZV8qIiaWiXxWIo6XQ="}}, "meta": {"description": "Syncs any local folder with the cloud", "homepage": "https://github.com/sebthedev/MacDropAny", "platforms": ["aarch64-darwin", "x86_64-darwin"]}, "passthru": {}}