{"name": "marginnote", "desktopName": "MarginNote", "version": "4.1.22", "aliases": ["marginnote"], "artifacts": {"apps": [{"source": "MarginNote 4.app"}], "binaries": [], "manPages": [], "files": [], "shellCompletionsBash": [], "shellCompletionsFish": [], "shellCompletionsZsh": []}, "files": {"aarch64-darwin": {"url": "https://dist.marginnote.cn/MarginNote4.1.22.dmg", "version": "4.1.22", "hash": "sha256-jYCpWf/u10975Wy2FILW7U/XJS7iP234sURXHNGJbMU="}, "x86_64-darwin": {"url": "https://dist.marginnote.cn/MarginNote4.1.22.dmg", "version": "4.1.22", "hash": "sha256-jYCpWf/u10975Wy2FILW7U/XJS7iP234sURXHNGJbMU="}}, "meta": {"description": "E-reader", "homepage": "https://www.marginnote.com/", "platforms": ["aarch64-darwin", "x86_64-darwin"], "broken": false}, "passthru": {}}