{"name": "ultracopier", "desktopName": "ultracopier", "version": "2.2.6.8", "aliases": ["ultracopier"], "artifacts": {"apps": [{"source": "ultracopier.app"}], "binaries": [], "manPages": [], "files": [], "shellCompletionsBash": [], "shellCompletionsFish": [], "shellCompletionsZsh": []}, "files": {"aarch64-darwin": {"url": "https://cdn.confiared.com/ultracopier.herman-brule.com/files/2.2.6.8/ultracopier-mac-os-x-2.2.6.8.dmg", "version": "2.2.6.8", "hash": "sha256-YBh1XxTXMVakundG5IG0ZvzwDe7DgF5qgwbI5ioDQAs="}, "x86_64-darwin": {"url": "https://cdn.confiared.com/ultracopier.herman-brule.com/files/2.2.6.8/ultracopier-mac-os-x-2.2.6.8.dmg", "version": "2.2.6.8", "hash": "sha256-YBh1XxTXMVakundG5IG0ZvzwDe7DgF5qgwbI5ioDQAs="}}, "meta": {"description": "Replacement for files copy dialogs", "homepage": "https://ultracopier.herman-brule.com/", "platforms": ["aarch64-darwin", "x86_64-darwin"]}, "passthru": {}}