{"name": "zipic", "desktopName": "Zipic", "version": "1.7.3", "aliases": ["zipic"], "artifacts": {"apps": [{"source": "Zipic.app"}], "binaries": [], "manPages": [], "files": [], "shellCompletionsBash": [], "shellCompletionsFish": [], "shellCompletionsZsh": []}, "files": {"aarch64-darwin": {"url": "https://zipic.5km.tech/Zipic%201.7.3.dmg", "version": "1.7.3", "hash": "sha256-3cZJ783cmb6hD8ipIDMbBBUBGgqoPiM35AssEFCA0dk="}, "x86_64-darwin": {"url": "https://zipic.5km.tech/Zipic%201.7.3.dmg", "version": "1.7.3", "hash": "sha256-3cZJ783cmb6hD8ipIDMbBBUBGgqoPiM35AssEFCA0dk="}}, "meta": {"description": "Image compression tool", "homepage": "https://zipic.5km.tech/", "platforms": ["aarch64-darwin", "x86_64-darwin"]}, "passthru": {}}