{"name": "voov-meeting", "desktopName": "VooV Meeting", "version": "3.32.0.510", "aliases": ["voov-meeting"], "artifacts": {"apps": [{"source": "VooV Meeting.app"}], "binaries": [], "manPages": [], "files": [], "shellCompletionsBash": [], "shellCompletionsFish": [], "shellCompletionsZsh": []}, "files": {"aarch64-darwin": {"url": "https://updatecdn.meeting.qq.com/cos/317322b4178d2b2074c7e555f2a221f8/VooVMeeting_1410000198_3.32.0.510.publish.arm64.dmg", "version": "3.32.0.510", "hash": "sha256-LgIHfN9uIxRiQpKIgpTwkrR7nCJOiFcxsgk1ZNmEa6Y="}, "x86_64-darwin": {"url": "https://updatecdn.meeting.qq.com/cos/317322b4178d2b2074c7e555f2a221f8/VooVMeeting_1410000198_3.32.0.510.publish.arm64.dmg", "version": "3.32.0.510", "hash": "sha256-LgIHfN9uIxRiQpKIgpTwkrR7nCJOiFcxsgk1ZNmEa6Y="}}, "meta": {"description": "Video conferencing software", "homepage": "https://voovmeeting.com/", "platforms": ["aarch64-darwin", "x86_64-darwin"], "broken": false}, "passthru": {}}