{"name": "singlebox", "desktopName": "Singlebox", "version": "60.18.0", "aliases": ["singlebox"], "artifacts": {"apps": [{"source": "Singlebox.app"}], "binaries": [], "manPages": [], "files": [], "shellCompletionsBash": [], "shellCompletionsFish": [], "shellCompletionsZsh": []}, "files": {"aarch64-darwin": {"url": "https://cdn-2.webcatalog.io/singlebox2/Singlebox-60.18.0-universal.dmg", "version": "60.18.0", "hash": "sha256-Br7tVXAi9E1CvT8MXpjkMvVbBUP8yRgr5ZGvw7f2xCs="}, "x86_64-darwin": {"url": "https://cdn-2.webcatalog.io/singlebox2/Singlebox-60.18.0-universal.dmg", "version": "60.18.0", "hash": "sha256-Br7tVXAi9E1CvT8MXpjkMvVbBUP8yRgr5ZGvw7f2xCs="}}, "meta": {"description": "Multi-account web browser", "homepage": "https://singlebox.app/en/"}, "passthru": {}}