{"name": "syncovery", "desktopName": "Syncovery", "version": "11.6.2", "aliases": ["syncovery"], "artifacts": {"apps": [], "binaries": [], "manPages": [], "files": [], "shellCompletionsBash": [], "shellCompletionsFish": [], "shellCompletionsZsh": []}, "files": {"aarch64-darwin": {"url": "https://www.syncovery.com/release/SyncoveryMac11.6.2-Apple.dmg", "version": "11.6.2", "hash": "sha256-CDIYeRNzqFwx8fr0PhhggJaXfOwNGG3nF8rZSAT4qHE="}, "x86_64-darwin": {"url": "https://www.syncovery.com/release/SyncoveryMac11.6.2-Apple.dmg", "version": "11.6.2", "hash": "sha256-CDIYeRNzqFwx8fr0PhhggJaXfOwNGG3nF8rZSAT4qHE="}}, "meta": {"description": "File synchronisation and backup software", "homepage": "https://www.syncovery.com/", "platforms": ["aarch64-darwin", "x86_64-darwin"]}, "passthru": {}}