{"name": "nault", "desktopName": "Nault", "version": "1.18.2", "aliases": ["nault"], "artifacts": {"apps": [{"source": "Nault.app"}], "binaries": [], "manPages": [], "files": [], "shellCompletionsBash": [], "shellCompletionsFish": [], "shellCompletionsZsh": []}, "files": {"aarch64-darwin": {"url": "https://github.com/Nault/Nault/releases/download/v1.18.2/Nault-1.18.2-Mac.dmg", "version": "1.18.2", "hash": "sha256-+KekiP4iDIRS35uAteF22k9IixxfQdflqA+gQPS+738="}, "x86_64-darwin": {"url": "https://github.com/Nault/Nault/releases/download/v1.18.2/Nault-1.18.2-Mac.dmg", "version": "1.18.2", "hash": "sha256-+KekiP4iDIRS35uAteF22k9IixxfQdflqA+gQPS+738="}}, "meta": {"description": "Wallet for the Nano cryptocurrency with support for hardware wallets", "homepage": "https://github.com/Nault/Nault", "platforms": ["aarch64-darwin", "x86_64-darwin"], "broken": false}, "passthru": {}}