{"name": "kakapo", "desktopName": "Kakapo", "version": "1.3.0", "aliases": ["kakapo"], "artifacts": {"apps": [{"source": "Kakapo.app"}], "binaries": [], "manPages": [], "files": [], "shellCompletionsBash": [], "shellCompletionsFish": [], "shellCompletionsZsh": []}, "files": {"aarch64-darwin": {"url": "https://github.com/bluedaniel/Kakapo-app/releases/download/v1.3.0/Kakapo-1.3.0-Mac.zip", "version": "1.3.0", "hash": "sha256-T4ny1lG4jnwTvOPMzvxJKeg6X1CdrhAvBx7NgKq51SQ="}, "x86_64-darwin": {"url": "https://github.com/bluedaniel/Kakapo-app/releases/download/v1.3.0/Kakapo-1.3.0-Mac.zip", "version": "1.3.0", "hash": "sha256-T4ny1lG4jnwTvOPMzvxJKeg6X1CdrhAvBx7NgKq51SQ="}}, "meta": {"description": "Open-source ambient sound mixer", "homepage": "https://github.com/bluedaniel/Kakapo-app", "platforms": ["aarch64-darwin", "x86_64-darwin"]}, "passthru": {}}