{"name": "kaku", "desktopName": "Kaku", "version": "2.0.2", "aliases": ["kaku"], "artifacts": {"apps": [{"source": "Kaku.app"}], "binaries": [], "manPages": [], "files": [], "shellCompletionsBash": [], "shellCompletionsFish": [], "shellCompletionsZsh": []}, "files": {"aarch64-darwin": {"url": "https://github.com/EragonJ/Kaku/releases/download/2.0.2/Kaku-2.0.2.dmg", "version": "2.0.2", "hash": "sha256-uonNWaSbfCHXzN4JBE4v7X4t7rYXeYrEUoH4MTDjE8o="}, "x86_64-darwin": {"url": "https://github.com/EragonJ/Kaku/releases/download/2.0.2/Kaku-2.0.2.dmg", "version": "2.0.2", "hash": "sha256-uonNWaSbfCHXzN4JBE4v7X4t7rYXeYrEUoH4MTDjE8o="}}, "meta": {"description": null, "homepage": "https://kaku.rocks/", "platforms": ["aarch64-darwin", "x86_64-darwin"]}, "passthru": {}}