{"name": "launchcontrol", "desktopName": "LaunchControl", "version": "2.8.4", "aliases": ["launchcontrol"], "artifacts": {"apps": [{"source": "LaunchControl.app"}], "binaries": [{"source": "$APPDIR/LaunchControl.app/Contents/MacOS/fdautil"}], "manPages": [], "files": [], "shellCompletionsBash": [], "shellCompletionsFish": [], "shellCompletionsZsh": []}, "files": {"aarch64-darwin": {"url": "https://www.soma-zone.com/download/files/LaunchControl-2.8.4.tar.xz", "version": "2.8.4", "hash": "sha256-fCtxJZiz1RYU7cJZ+Vb6cCzTzwSLRmCK7K0ptWxZ8/s="}, "x86_64-darwin": {"url": "https://www.soma-zone.com/download/files/LaunchControl-2.8.4.tar.xz", "version": "2.8.4", "hash": "sha256-fCtxJZiz1RYU7cJZ+Vb6cCzTzwSLRmCK7K0ptWxZ8/s="}}, "meta": {"description": "Create, manage and debug system and user services", "homepage": "https://www.soma-zone.com/LaunchControl/", "platforms": ["aarch64-darwin", "x86_64-darwin"], "broken": false}, "passthru": {}}