{"name": "stability-matrix", "desktopName": "Stability Matrix", "version": "2.14.3", "aliases": ["stability-matrix"], "artifacts": {"apps": [{"source": "Stability Matrix.app"}], "binaries": [], "manPages": [], "files": [], "shellCompletionsBash": [], "shellCompletionsFish": [], "shellCompletionsZsh": []}, "files": {"aarch64-darwin": {"url": "https://github.com/LykosAI/StabilityMatrix/releases/download/v2.14.3/StabilityMatrix-macos-arm64.dmg", "version": "2.14.3", "hash": "sha256-oiQW7LQcSOKxRQowopACbyx0tm1m8ktWmgxf2P3Dsog="}, "x86_64-darwin": {"url": "https://github.com/LykosAI/StabilityMatrix/releases/download/v2.14.3/StabilityMatrix-macos-arm64.dmg", "version": "2.14.3", "hash": "sha256-oiQW7LQcSOKxRQowopACbyx0tm1m8ktWmgxf2P3Dsog="}}, "meta": {"description": "Package manager and inference UI for Stable Diffusion", "homepage": "https://github.com/LykosAI/StabilityMatrix", "platforms": ["aarch64-darwin", "x86_64-darwin"], "broken": false}, "passthru": {}}