{"name": "ckb-next", "desktopName": "ckb-next", "version": "0.4.4", "aliases": ["ckb-next"], "artifacts": {"apps": [], "binaries": [], "manPages": [], "files": [], "shellCompletionsBash": [], "shellCompletionsFish": [], "shellCompletionsZsh": []}, "files": {"aarch64-darwin": {"url": "https://github.com/ckb-next/ckb-next/releases/download/v0.4.4/ckb-next_v0.4.4.dmg", "version": "0.4.4", "hash": "sha256-KnYhgVJbpLHyapWzdLq+SP8NWQ8dNrwQl0nIRcilcJA="}, "x86_64-darwin": {"url": "https://github.com/ckb-next/ckb-next/releases/download/v0.4.4/ckb-next_v0.4.4.dmg", "version": "0.4.4", "hash": "sha256-KnYhgVJbpLHyapWzdLq+SP8NWQ8dNrwQl0nIRcilcJA="}}, "meta": {"description": "RGB driver", "homepage": "https://github.com/ckb-next/ckb-next"}, "passthru": {}}