{"name": "smartgit", "desktopName": "SmartGit", "version": "24.1.4", "aliases": ["smartgit"], "artifacts": {"apps": [{"source": "SmartGit.app"}], "binaries": [{"source": "$APPDIR/SmartGit.app/Contents/MacOS/SmartGit"}], "manPages": [], "files": [], "shellCompletionsBash": [], "shellCompletionsFish": [], "shellCompletionsZsh": []}, "files": {"aarch64-darwin": {"url": "https://www.syntevo.com/downloads/smartgit/smartgit-aarch64-24_1_4.dmg", "version": "24.1.4", "hash": "sha256-MwJ0upkj1kKYytkoAmw9tp/jqJnaxejLmVzL5mRMSMA="}, "x86_64-darwin": {"url": "https://www.syntevo.com/downloads/smartgit/smartgit-aarch64-24_1_4.dmg", "version": "24.1.4", "hash": "sha256-MwJ0upkj1kKYytkoAmw9tp/jqJnaxejLmVzL5mRMSMA="}}, "meta": {"description": "Git client", "homepage": "https://www.syntevo.com/smartgit/", "platforms": ["aarch64-darwin", "x86_64-darwin"]}, "passthru": {}}