{"name": "lunasea", "desktopName": "LunaSea", "version": "11.0.0", "aliases": ["lunasea"], "artifacts": {"apps": [{"source": "LunaSea.app"}], "binaries": [], "manPages": [], "files": [], "shellCompletionsBash": [], "shellCompletionsFish": [], "shellCompletionsZsh": []}, "files": {"aarch64-darwin": {"url": "https://github.com/JagandeepBrar/LunaSea/releases/download/v11.0.0/lunasea-macos-amd64.zip", "version": "11.0.0", "hash": "sha256-+k7LW99X1vEybjVuJIIyBA8bLQ1Anqk6yW3FYO3tmAw="}, "x86_64-darwin": {"url": "https://github.com/JagandeepBrar/LunaSea/releases/download/v11.0.0/lunasea-macos-amd64.zip", "version": "11.0.0", "hash": "sha256-+k7LW99X1vEybjVuJIIyBA8bLQ1Anqk6yW3FYO3tmAw="}}, "meta": {"description": "Self-hosted controller built using the Flutter framework", "homepage": "https://www.lunasea.app/", "platforms": ["aarch64-darwin", "x86_64-darwin"]}, "passthru": {}}