{"name": "energybar", "desktopName": "EnergyBar", "version": "1.7.19321", "aliases": ["energybar"], "artifacts": {"apps": [{"source": "EnergyBar.app"}], "binaries": [], "manPages": [], "files": [], "shellCompletionsBash": [], "shellCompletionsFish": [], "shellCompletionsZsh": []}, "files": {"aarch64-darwin": {"url": "https://github.com/billziss-gh/EnergyBar/releases/download/v1.7/EnergyBar-1.7.19321.zip", "version": "1.7.19321", "hash": "sha256-lsBqk9WRYAEwavQBBGKVkmvziZbXZzZcGZEx4GjYVic="}, "x86_64-darwin": {"url": "https://github.com/billziss-gh/EnergyBar/releases/download/v1.7/EnergyBar-1.7.19321.zip", "version": "1.7.19321", "hash": "sha256-lsBqk9WRYAEwavQBBGKVkmvziZbXZzZcGZEx4GjYVic="}}, "meta": {"description": "Touch Bar widget application", "homepage": "https://github.com/billziss-gh/EnergyBar", "platforms": ["aarch64-darwin", "x86_64-darwin"], "broken": false}, "passthru": {}}