{"name": "deviceinfo", "desktopName": "DeviceInfo", "version": "1.0", "aliases": ["deviceinfo"], "artifacts": {"apps": [{"source": "DeviceInfo.app"}], "binaries": [], "manPages": [], "files": [], "shellCompletionsBash": [], "shellCompletionsFish": [], "shellCompletionsZsh": []}, "files": {"aarch64-darwin": {"url": "https://github.com/CoreNion/DeviceInfo/releases/download/v1.0/DeviceInfo.dmg", "version": "1.0", "hash": "sha256-A4fj1aEgJ9gHvI6E0RyK4GL+9Wyhu8u6ZeDsyDmJ7V4="}, "x86_64-darwin": {"url": "https://github.com/CoreNion/DeviceInfo/releases/download/v1.0/DeviceInfo.dmg", "version": "1.0", "hash": "sha256-A4fj1aEgJ9gHvI6E0RyK4GL+9Wyhu8u6ZeDsyDmJ7V4="}}, "meta": {"description": "Display device information", "homepage": "https://github.com/CoreNion/DeviceInfo/", "platforms": ["aarch64-darwin", "x86_64-darwin"], "broken": false}, "passthru": {}}