{"name": "devonsphere-express", "desktopName": "DEVONsphere Express", "version": "1.9.8", "aliases": ["devonsphere-express"], "artifacts": {"apps": [{"source": "DEVONsphere Express.app"}], "binaries": [], "manPages": [], "files": [], "shellCompletionsBash": [], "shellCompletionsFish": [], "shellCompletionsZsh": []}, "files": {"aarch64-darwin": {"url": "https://download.devontechnologies.com/download/devonsphere/1.9.8/DEVONsphere_Express.app.zip", "version": "1.9.8", "hash": "sha256-qbrpKL9YwaXLsRh4wwbsHno9K9xd4+XQgPKRxTY8aZc="}, "x86_64-darwin": {"url": "https://download.devontechnologies.com/download/devonsphere/1.9.8/DEVONsphere_Express.app.zip", "version": "1.9.8", "hash": "sha256-qbrpKL9YwaXLsRh4wwbsHno9K9xd4+XQgPKRxTY8aZc="}}, "meta": {"description": "Find items related to the frontmost document locally or online", "homepage": "https://www.devontechnologies.com/apps/devonsphere", "platforms": ["aarch64-darwin", "x86_64-darwin"], "broken": false}, "passthru": {}}