{"name": "beaver-notes", "desktopName": "Beaver Notes", "version": "4.1.0", "aliases": ["beaver-notes"], "artifacts": {"apps": [{"source": "Beaver-notes.app"}], "binaries": [], "manPages": [], "files": [], "shellCompletionsBash": [], "shellCompletionsFish": [], "shellCompletionsZsh": []}, "files": {"aarch64-darwin": {"url": "https://github.com/Beaver-Notes/Beaver-Notes/releases/download/4.1.0/Beaver-notes-4.1.0-universal.dmg", "version": "4.1.0", "hash": "sha256-uBmLQYXBhUrLCcro5+KfKpklqe4dGqaguCgddmSxXpQ="}, "x86_64-darwin": {"url": "https://github.com/Beaver-Notes/Beaver-Notes/releases/download/4.1.0/Beaver-notes-4.1.0-universal.dmg", "version": "4.1.0", "hash": "sha256-uBmLQYXBhUrLCcro5+KfKpklqe4dGqaguCgddmSxXpQ="}}, "meta": {"description": "Privacy-focused note-taking app", "homepage": "https://beavernotes.com/", "platforms": ["aarch64-darwin", "x86_64-darwin"]}, "passthru": {}}