{"name": "beyond-compare", "desktopName": "Beyond Compare", "version": "5.1.3.31238", "aliases": ["beyond-compare"], "artifacts": {"apps": [{"source": "Beyond Compare.app"}], "binaries": [{"source": "$APPDIR/Beyond Compare.app/Contents/MacOS/bcomp"}], "manPages": [], "files": [], "shellCompletionsBash": [], "shellCompletionsFish": [], "shellCompletionsZsh": []}, "files": {"aarch64-darwin": {"url": "https://www.scootersoftware.com/files/BCompareOSX-5.1.3.31238.zip", "version": "5.1.3.31238", "hash": "sha256-DXnZKqffBp6CEC5gSfqkTSjtRGNmMmhbXYe9rxoH18A="}, "x86_64-darwin": {"url": "https://www.scootersoftware.com/files/BCompareOSX-5.1.3.31238.zip", "version": "5.1.3.31238", "hash": "sha256-DXnZKqffBp6CEC5gSfqkTSjtRGNmMmhbXYe9rxoH18A="}}, "meta": {"description": "Compare files and folders", "homepage": "https://www.scootersoftware.com/"}, "passthru": {}}