{"name": "filemaker-pro", "desktopName": "FileMaker Pro", "version": "22.0.2.202", "aliases": ["filemaker-pro"], "artifacts": {"apps": [{"source": "FileMaker Pro.app"}], "binaries": [], "manPages": [], "files": [], "shellCompletionsBash": [], "shellCompletionsFish": [], "shellCompletionsZsh": []}, "files": {"aarch64-darwin": {"url": "https://downloads.claris.com/esd/fmp_22.0.2.202.dmg", "version": "22.0.2.202", "hash": "sha256-eMHEeMWajygBic+bYWu/Xq+2x+xnTALVx9F2L7r7KM8="}, "x86_64-darwin": {"url": "https://downloads.claris.com/esd/fmp_22.0.2.202.dmg", "version": "22.0.2.202", "hash": "sha256-eMHEeMWajygBic+bYWu/Xq+2x+xnTALVx9F2L7r7KM8="}}, "meta": {"description": "Relational database and rapid application development platform", "homepage": "https://www.claris.com/filemaker/"}, "passthru": {}}