{"name": "firebase-admin", "desktopName": "Firebase Admin", "version": "1.0.1", "aliases": ["firebase-admin"], "artifacts": {"apps": [{"source": "firebase-admin.app"}], "binaries": [], "manPages": [], "files": [], "shellCompletionsBash": [], "shellCompletionsFish": [], "shellCompletionsZsh": []}, "files": {"aarch64-darwin": {"url": "https://firebaseadmin.com/downloads/1.0.1/firebase-admin-mac-1.0.1.dmg", "version": "1.0.1", "hash": "sha256-seVogV0YLNLTiAHvjRtI4bpExPPz09wwhIJ+oZ9gtkw="}, "x86_64-darwin": {"url": "https://firebaseadmin.com/downloads/1.0.1/firebase-admin-mac-1.0.1.dmg", "version": "1.0.1", "hash": "sha256-seVogV0YLNLTiAHvjRtI4bpExPPz09wwhIJ+oZ9gtkw="}}, "meta": {"description": "Admin user interface for Firebase", "homepage": "https://firebaseadmin.com/", "platforms": ["aarch64-darwin", "x86_64-darwin"]}, "passthru": {}}