{"name": "sqlpro-for-mysql", "desktopName": "SQLPro for MySQL", "version": "2025.10", "aliases": ["sqlpro-for-mysql"], "artifacts": {"apps": [{"source": "SQLPro for MySQL.app"}], "binaries": [], "manPages": [], "files": [], "shellCompletionsBash": [], "shellCompletionsFish": [], "shellCompletionsZsh": []}, "files": {"aarch64-darwin": {"url": "https://d3fwkemdw8spx3.cloudfront.net/mysql/SQLProMySQL.2025.10.app.zip", "version": "2025.10", "hash": "sha256-qj3CS9irHKYrOc9FGeSvQJgkOAKf/V0dzvvfABxmbR8="}, "x86_64-darwin": {"url": "https://d3fwkemdw8spx3.cloudfront.net/mysql/SQLProMySQL.2025.10.app.zip", "version": "2025.10", "hash": "sha256-qj3CS9irHKYrOc9FGeSvQJgkOAKf/V0dzvvfABxmbR8="}}, "meta": {"description": "MySQL & MariaDB database client", "homepage": "https://www.mysqlui.com/", "platforms": ["aarch64-darwin", "x86_64-darwin"]}, "passthru": {}}