{"name": "tiny-shield", "desktopName": "Tiny Shield", "version": "1.2.1", "aliases": ["tiny-shield"], "artifacts": {"apps": [{"source": "Tiny Shield.app"}], "binaries": [], "manPages": [], "files": [], "shellCompletionsBash": [], "shellCompletionsFish": [], "shellCompletionsZsh": []}, "files": {"aarch64-darwin": {"url": "https://download.proxyman.io/tinyshield/10201/Tiny_Shield_1.2.1.dmg", "version": "1.2.1", "hash": "sha256-uSir4sOkR6yr9+G/vRqT6MMjH/kPXp1TIMqzbVK/+1s="}, "x86_64-darwin": {"url": "https://download.proxyman.io/tinyshield/10201/Tiny_Shield_1.2.1.dmg", "version": "1.2.1", "hash": "sha256-uSir4sOkR6yr9+G/vRqT6MMjH/kPXp1TIMqzbVK/+1s="}}, "meta": {"description": "Control and monitor network connections", "homepage": "https://tinyshield.proxyman.com/"}, "passthru": {}}