{"name": "tiptoi-manager", "desktopName": "tiptoi Manager", "version": "5.2", "aliases": ["tiptoi-manager"], "artifacts": {"apps": [], "binaries": [], "manPages": [], "files": [], "shellCompletionsBash": [], "shellCompletionsFish": [], "shellCompletionsZsh": []}, "files": {"aarch64-darwin": null, "x86_64-darwin": null}, "meta": {"description": "Manage the data on children's Ravensburger tip toi audio pen", "homepage": "https://service.ravensburger.de/tiptoi%25C2%25AE/tiptoi_Manager", "platforms": ["aarch64-darwin", "x86_64-darwin"]}, "passthru": {}}