{"name": "chromedriver", "desktopName": "ChromeDriver", "version": "139.0.7258.68", "aliases": ["chromedriver"], "artifacts": {"apps": [], "binaries": [{"source": "chromedriver-mac-arm64/chromedriver"}], "manPages": [], "files": [], "shellCompletionsBash": [], "shellCompletionsFish": [], "shellCompletionsZsh": []}, "files": {"aarch64-darwin": {"url": "https://storage.googleapis.com/chrome-for-testing-public/139.0.7258.68/mac-arm64/chromedriver-mac-arm64.zip", "version": "139.0.7258.68", "hash": "sha256-bahQUI0lDADBCwncrADJeljVE0YEeXLCxH0+O4UNRmI="}, "x86_64-darwin": {"url": "https://storage.googleapis.com/chrome-for-testing-public/139.0.7258.68/mac-arm64/chromedriver-mac-arm64.zip", "version": "139.0.7258.68", "hash": "sha256-bahQUI0lDADBCwncrADJeljVE0YEeXLCxH0+O4UNRmI="}}, "meta": {"description": "Automated testing of webapps for Google Chrome", "homepage": "https://chromedriver.chromium.org/", "platforms": ["aarch64-darwin", "x86_64-darwin"], "broken": false}, "passthru": {}}