{"name": "flowvision", "desktopName": "FlowVision", "version": "1.6.6", "aliases": ["flowvision"], "artifacts": {"apps": [{"source": "FlowVision.app"}], "binaries": [], "manPages": [], "files": [], "shellCompletionsBash": [], "shellCompletionsFish": [], "shellCompletionsZsh": []}, "files": {"aarch64-darwin": {"url": "https://github.com/netdcy/FlowVision/releases/download/1.6.6/FlowVision.1.6.6.zip", "version": "1.6.6", "hash": "sha256-YEiIfo0PzEeP/D6/N2uKToLlDO62aT99CscobAeYmH4="}, "x86_64-darwin": {"url": "https://github.com/netdcy/FlowVision/releases/download/1.6.6/FlowVision.1.6.6.zip", "version": "1.6.6", "hash": "sha256-YEiIfo0PzEeP/D6/N2uKToLlDO62aT99CscobAeYmH4="}}, "meta": {"description": "Waterfall-style image viewer", "homepage": "https://flowvision.app/", "platforms": ["aarch64-darwin", "x86_64-darwin"], "broken": false}, "passthru": {}}