{"name": "fluent-reader", "desktopName": "Fluent Reader", "version": "1.1.4", "aliases": ["fluent-reader"], "artifacts": {"apps": [{"source": "Fluent Reader.app"}], "binaries": [], "manPages": [], "files": [], "shellCompletionsBash": [], "shellCompletionsFish": [], "shellCompletionsZsh": []}, "files": {"aarch64-darwin": {"url": "https://github.com/yang991178/fluent-reader/releases/download/v1.1.4/Fluent.Reader.1.1.4.dmg", "version": "1.1.4", "hash": "sha256-zcrCrXGZshS+HE/g8PDJNshu+HwuFz+4fpOVZSOZytY="}, "x86_64-darwin": {"url": "https://github.com/yang991178/fluent-reader/releases/download/v1.1.4/Fluent.Reader.1.1.4.dmg", "version": "1.1.4", "hash": "sha256-zcrCrXGZshS+HE/g8PDJNshu+HwuFz+4fpOVZSOZytY="}}, "meta": {"description": "RSS/Atom news aggregator", "homepage": "https://hyliu.me/fluent-reader/", "platforms": ["aarch64-darwin", "x86_64-darwin"], "broken": false}, "passthru": {}}