{"name": "netnewswire@beta", "desktopName": "NetNewsWire", "version": "6.1.10b4", "aliases": ["netnewswire@beta"], "artifacts": {"apps": [{"source": "NetNewsWire.app"}], "binaries": [], "manPages": [], "files": [], "shellCompletionsBash": [], "shellCompletionsFish": [], "shellCompletionsZsh": []}, "files": {"aarch64-darwin": {"url": "https://github.com/brentsimmons/NetNewsWire/releases/download/mac-6.1.10b4/NetNewsWire6.1.10b4.zip", "version": "6.1.10b4", "hash": "sha256-vBXzSPlujSv3CzUnrxd8HLFy2Kivr4IJGQ2AhEpX3fw="}, "x86_64-darwin": {"url": "https://github.com/brentsimmons/NetNewsWire/releases/download/mac-6.1.10b4/NetNewsWire6.1.10b4.zip", "version": "6.1.10b4", "hash": "sha256-vBXzSPlujSv3CzUnrxd8HLFy2Kivr4IJGQ2AhEpX3fw="}}, "meta": {"description": "Free and open-source RSS reader", "homepage": "https://ranchero.com/netnewswire/"}, "passthru": {}}