{"name": "clips-ide", "desktopName": "CLIPS IDE", "version": "6.4.2", "aliases": ["clips-ide"], "artifacts": {"apps": [{"source": "CLIPS IDE.app"}], "binaries": [], "manPages": [], "files": [], "shellCompletionsBash": [], "shellCompletionsFish": [], "shellCompletionsZsh": []}, "files": {"aarch64-darwin": {"url": "https://downloads.sourceforge.net/clipsrules/clips_macos_executable_642.dmg", "version": "6.4.2", "hash": "sha256-SNvnP16R5ZQWSN9cljZxe4WHKJU6mDEaAAkn5qkdsiM="}, "x86_64-darwin": {"url": "https://downloads.sourceforge.net/clipsrules/clips_macos_executable_642.dmg", "version": "6.4.2", "hash": "sha256-SNvnP16R5ZQWSN9cljZxe4WHKJU6mDEaAAkn5qkdsiM="}}, "meta": {"description": "Tool for building expert systems", "homepage": "https://www.clipsrules.net/", "platforms": ["aarch64-darwin", "x86_64-darwin"]}, "passthru": {}}