{"name": "notion-mail", "desktopName": "Notion Mail", "version": "0.0.37", "aliases": ["notion-mail"], "artifacts": {"apps": [{"source": "Notion Mail.app"}], "binaries": [], "manPages": [], "files": [], "shellCompletionsBash": [], "shellCompletionsFish": [], "shellCompletionsZsh": []}, "files": {"aarch64-darwin": {"url": "https://mail-desktop-release.notion-static.com/Notion%20Mail-0.0.37-arm64.zip", "version": "0.0.37", "hash": "sha256-1m/DA3kfasGUDIQNqxzEuI12x3gGh3c0YWZ/sBHcRwA="}, "x86_64-darwin": {"url": "https://mail-desktop-release.notion-static.com/Notion%20Mail-0.0.37-arm64.zip", "version": "0.0.37", "hash": "sha256-1m/DA3kfasGUDIQNqxzEuI12x3gGh3c0YWZ/sBHcRwA="}}, "meta": {"description": "Email client integrated with Notion workspace", "homepage": "https://www.notion.com/product/mail"}, "passthru": {}}