{"name": "hydrus-network", "desktopName": "hydrus network", "version": "635", "aliases": ["hydrus-network"], "artifacts": {"apps": [{"source": "Hydrus Network.app"}], "binaries": [], "manPages": [], "files": [], "shellCompletionsBash": [], "shellCompletionsFish": [], "shellCompletionsZsh": []}, "files": {"aarch64-darwin": {"url": "https://github.com/hydrusnetwork/hydrus/releases/download/v635/Hydrus.Network.635.-.macOS.-.App.zip", "version": "635", "hash": "sha256-AAsyy/cd4Uoi0l2u4/2EcpZ+7wFA63cU6OCpgUuS7xU="}, "x86_64-darwin": {"url": "https://github.com/hydrusnetwork/hydrus/releases/download/v635/Hydrus.Network.635.-.macOS.-.App.zip", "version": "635", "hash": "sha256-AAsyy/cd4Uoi0l2u4/2EcpZ+7wFA63cU6OCpgUuS7xU="}}, "meta": {"description": "Booru-style media tagger", "homepage": "https://hydrusnetwork.github.io/hydrus/"}, "passthru": {}}