{"name": "skint", "desktopName": "Skint", "version": "1.08", "aliases": ["skint"], "artifacts": {"apps": [{"source": "skint108/Skint.app"}, {"source": "skint108/SkintM.app"}], "binaries": [], "manPages": [], "files": [], "shellCompletionsBash": [], "shellCompletionsFish": [], "shellCompletionsZsh": []}, "files": {"aarch64-darwin": {"url": "https://eclecticlight.co/wp-content/uploads/2024/08/skint108.zip", "version": "1.08", "hash": "sha256-8BmvMbols8H5PZTlzVdk1JvTD569H0ThOARlTzs5lUg="}, "x86_64-darwin": {"url": "https://eclecticlight.co/wp-content/uploads/2024/08/skint108.zip", "version": "1.08", "hash": "sha256-8BmvMbols8H5PZTlzVdk1JvTD569H0ThOARlTzs5lUg="}}, "meta": {"description": "Check status of key security settings and features", "homepage": "https://eclecticlight.co/lockrattler-systhist/"}, "passthru": {}}