{"name": "lectrote", "desktopName": "Lectrote", "version": "1.5.5", "aliases": ["lectrote"], "artifacts": {"apps": [{"source": "Lectrote.app"}], "binaries": [], "manPages": [], "files": [], "shellCompletionsBash": [], "shellCompletionsFish": [], "shellCompletionsZsh": []}, "files": {"aarch64-darwin": {"url": "https://github.com/erkyrath/lectrote/releases/download/lectrote-1.5.5/Lectrote-1.5.5-macos-arm64.dmg", "version": "1.5.5", "hash": "sha256-QkU2ClRV8h7n8it4r1bAo1Qi6GrbJPgNYdw3ZLNP1QQ="}, "x86_64-darwin": {"url": "https://github.com/erkyrath/lectrote/releases/download/lectrote-1.5.5/Lectrote-1.5.5-macos-arm64.dmg", "version": "1.5.5", "hash": "sha256-QkU2ClRV8h7n8it4r1bAo1Qi6GrbJPgNYdw3ZLNP1QQ="}}, "meta": {"description": "Interactive Fiction interpreter in an Electron shell", "homepage": "https://github.com/erkyrath/lectrote", "platforms": ["aarch64-darwin", "x86_64-darwin"], "broken": false}, "passthru": {}}