{"name": "daedalus-mainnet", "desktopName": "Daedalus Mainnet", "version": "7.1.0", "aliases": ["daedalus-mainnet"], "artifacts": {"apps": [], "binaries": [], "manPages": [], "files": [], "shellCompletionsBash": [], "shellCompletionsFish": [], "shellCompletionsZsh": []}, "files": {"aarch64-darwin": {"url": "https://update-cardano-mainnet.iohk.io/daedalus-7.1.0-72909-mainnet-5472147d9-x86_64-darwin.pkg", "version": "7.1.0", "hash": "sha256-yH83aM1JPTgsXh0DU4bCgAF/VmV0Mpr+T2fJIYjpaeU="}, "x86_64-darwin": {"url": "https://update-cardano-mainnet.iohk.io/daedalus-7.1.0-72909-mainnet-5472147d9-x86_64-darwin.pkg", "version": "7.1.0", "hash": "sha256-yH83aM1JPTgsXh0DU4bCgAF/VmV0Mpr+T2fJIYjpaeU="}}, "meta": {"description": "Cryptocurrency wallet for ada on the Cardano blockchain", "homepage": "https://daedaluswallet.io/"}, "passthru": {}}