{"name": "morkro-papyrus", "desktopName": "Papyrus", "version": "1.0.3", "aliases": ["morkro-papyrus"], "artifacts": {"apps": [{"source": "Papyrus.app"}], "binaries": [], "manPages": [], "files": [], "shellCompletionsBash": [], "shellCompletionsFish": [], "shellCompletionsZsh": []}, "files": {"aarch64-darwin": {"url": "https://github.com/morkro/papyrus/releases/download/1.0.3/Papyrus-osx-1.0.3.zip", "version": "1.0.3", "hash": "sha256-YTDg2TSG256WloYnDo7d3Jvha1KzQv200x60VG0WERg="}, "x86_64-darwin": {"url": "https://github.com/morkro/papyrus/releases/download/1.0.3/Papyrus-osx-1.0.3.zip", "version": "1.0.3", "hash": "sha256-YTDg2TSG256WloYnDo7d3Jvha1KzQv200x60VG0WERg="}}, "meta": {"description": "Unofficial Dropbox Paper desktop app", "homepage": "https://github.com/morkro/papyrus", "platforms": ["aarch64-darwin", "x86_64-darwin"], "broken": false}, "passthru": {}}