{"name": "reflex-app", "desktopName": "Reflex", "version": "1.2", "aliases": ["reflex-app", "reflex"], "artifacts": {"apps": [{"source": "Reflex.app"}], "binaries": [], "manPages": [], "files": [], "shellCompletionsBash": [], "shellCompletionsFish": [], "shellCompletionsZsh": []}, "files": {"aarch64-darwin": {"url": "https://stuntsoftware.com/download/reflex_1.2.zip", "version": "1.2", "hash": "sha256-WhkhFZVKKNzPKeqRpB8iavckrB/zKTYuJvxJUHPgQko="}, "x86_64-darwin": {"url": "https://stuntsoftware.com/download/reflex_1.2.zip", "version": "1.2", "hash": "sha256-WhkhFZVKKNzPKeqRpB8iavckrB/zKTYuJvxJUHPgQko="}}, "meta": {"description": "Media key forwarder for Music (iTunes) and Spotify", "homepage": "https://stuntsoftware.com/reflex/"}, "passthru": {}}