{"name": "vnc-server", "desktopName": "Real VNC Server", "version": "7.15.0", "aliases": ["vnc-server"], "artifacts": {"apps": [], "binaries": [], "manPages": [], "files": [], "shellCompletionsBash": [], "shellCompletionsFish": [], "shellCompletionsZsh": []}, "files": {"aarch64-darwin": {"url": "https://downloads.realvnc.com/download/file/vnc.files/VNC-Server-7.15.0-MacOSX-universal.pkg", "version": "7.15.0", "hash": "sha256-az+owsds/wTL1LKf76Lj4tqnvMo66pF+KhPj6DtTaNw="}, "x86_64-darwin": {"url": "https://downloads.realvnc.com/download/file/vnc.files/VNC-Server-7.15.0-MacOSX-universal.pkg", "version": "7.15.0", "hash": "sha256-az+owsds/wTL1LKf76Lj4tqnvMo66pF+KhPj6DtTaNw="}}, "meta": {"description": "Remote desktop server application", "homepage": "https://www.realvnc.com/"}, "passthru": {}}