{"name": "toptracker", "desktopName": "TopTracker", "version": "1.6.2", "aliases": ["toptracker"], "artifacts": {"apps": [{"source": "TopTracker.app"}], "binaries": [], "manPages": [], "files": [], "shellCompletionsBash": [], "shellCompletionsFish": [], "shellCompletionsZsh": []}, "files": {"aarch64-darwin": {"url": "https://d101nvfmxunqnl.cloudfront.net/desktop/builds/mac/toptracker_1.6.2.6524.dmg", "version": "1.6.2", "hash": "sha256-O2JvOkdhtv2GeNpN/tW+q98eoZhHiopfOgZYXeVoBLA="}, "x86_64-darwin": {"url": "https://d101nvfmxunqnl.cloudfront.net/desktop/builds/mac/toptracker_1.6.2.6524.dmg", "version": "1.6.2", "hash": "sha256-O2JvOkdhtv2GeNpN/tW+q98eoZhHiopfOgZYXeVoBLA="}}, "meta": {"description": "Time tracking and invoice processing", "homepage": "https://tracker.toptal.com/tracker/"}, "passthru": {}}