{"name": "espresso", "desktopName": "Espresso", "version": "5.9.1", "aliases": ["espresso"], "artifacts": {"apps": [{"source": "Espresso.app"}], "binaries": [], "manPages": [], "files": [], "shellCompletionsBash": [], "shellCompletionsFish": [], "shellCompletionsZsh": []}, "files": {"aarch64-darwin": {"url": "https://downloads.espressoapps.au/Espresso/Espresso_5.9.1.zip", "version": "5.9.1", "hash": "sha256-G9a8UQ7LSupyTO1lcW91l8D+J0nuH9jwX8ytVjNvph4="}, "x86_64-darwin": {"url": "https://downloads.espressoapps.au/Espresso/Espresso_5.9.1.zip", "version": "5.9.1", "hash": "sha256-G9a8UQ7LSupyTO1lcW91l8D+J0nuH9jwX8ytVjNvph4="}}, "meta": {"description": "Website editor focusing on flair and efficiency", "homepage": "https://espressoapp.com/", "platforms": ["aarch64-darwin", "x86_64-darwin"], "broken": false}, "passthru": {}}