{"name": "ableton-live-intro", "desktopName": "Ableton Live Intro", "version": "12.2.2", "aliases": ["ableton-live-intro"], "artifacts": {"apps": [{"source": "Ableton Live 12 Intro.app"}], "binaries": [], "manPages": [], "files": [], "shellCompletionsBash": [], "shellCompletionsFish": [], "shellCompletionsZsh": []}, "files": {"aarch64-darwin": {"url": "https://cdn-downloads.ableton.com/channels/12.2.2/ableton_live_intro_12.2.2_universal.dmg", "version": "12.2.2", "hash": "sha256-DNCuyMynDombZZLkooqaUDZAiB2d1ZWLd9gqxBZ8FQw="}, "x86_64-darwin": {"url": "https://cdn-downloads.ableton.com/channels/12.2.2/ableton_live_intro_12.2.2_universal.dmg", "version": "12.2.2", "hash": "sha256-DNCuyMynDombZZLkooqaUDZAiB2d1ZWLd9gqxBZ8FQw="}}, "meta": {"description": "Sound and music editor", "homepage": "https://www.ableton.com/en/live/", "platforms": ["aarch64-darwin", "x86_64-darwin"], "broken": false}, "passthru": {}}